{
  "countNames":100,
  "names":[
    {
      "name":"Fizban"
    },
    {
      "name":"Tasha"
    },
    {
      "name":"Trovik"
    },
    {
      "name":"Tex"
    },
    {
      "name":"Ladoux"
    },
    {
      "name":"Catch"
    },
    {
      "name":"Egrath"
    },
    {
      "name":"Dukoth"
    },
    {
      "name":"Vagaduur"
    },
    {
      "name":"Sorthremoth"
    },

    {
      "name":"Datain"
    },
    {
      "name":"Fafnir"
    },
    {
      "name":"Xanathar"
    },
    {
      "name":"Ulieth"
    },
    {
      "name":"Iolas"
    },
    {
      "name":"Tiarsus"
    },
    {
      "name":"Aerith"
    },
    {
      "name":"Aerendyl"
    },
    {
      "name":"Tanathil"
    },
    {
      "name":"Naesala"
    },

    {
      "name":"Ukdrik"
    },
    {
      "name":"Bhagromi"
    },
    {
      "name":"Stoneshorn"
    },
    {
      "name":"Coaldigger"
    },
    {
      "name":"Strong-in-the-Arm"
    },
    {
      "name":"Daragrik"
    },
    {
      "name":"Ironfinger"
    },
    {
      "name":"Kagnoid"
    },
    {
      "name":"Acerak"
    },
    {
      "name":"Volo"
    },

    {
      "name":"Mordenkainen"
    },
    {
      "name":"Strixhaven"
    },
    {
      "name":"Ravnica"
    },
    {
      "name":"Theros"
    },
    {
      "name":"Van Richten"
    },
    {
      "name":"Strahd"
    },
    {
      "name":"Uk"
    },
    {
      "name":"Rozlin"
    },
    {
      "name":"Thri"
    },
    {
      "name":"Burr"
    },

    {
      "name":"de Rolo"
    },
    {
      "name":"Mercer"
    },
    {
      "name":"Clay"
    },
    {
      "name":"Stone"
    },
    {
      "name":"Goat"
    },
    {
      "name":"Badjur"
    },
    {
      "name":"Foster"
    },
    {
      "name":"Taliesin"
    },
    {
      "name":"Underburrow"
    },
    {
      "name":"Barrowes"
    },

    {
      "name":"Sandyman"
    },
    {
      "name":"Sergui"
    },
    {
      "name":"Chararic"
    },
    {
      "name":"Munderic"
    },
    {
      "name":"Matta"
    },
    {
      "name":"Sadoc"
    },
    {
      "name":"Wandrille"
    },
    {
      "name":"Baldechildes"
    },
    {
      "name":"Qizuk"
    },
    {
      "name":"Moltenmaw"
    },

    {
      "name":"Crerc"
    },
    {
      "name":"Shrerrig"
    },
    {
      "name":"Kheng"
    },
    {
      "name":"Liu Deng"
    },
    {
      "name":"Shreabi"
    },
    {
      "name":"Dhahn"
    },
    {
      "name":"Velgrark"
    },
    {
      "name":"Mukcut"
    },
    {
      "name":"Wig"
    },
    {
      "name":"Krekor"
    },

    {
      "name":"Weurth"
    },
    {
      "name":"Gubog"
    },
    {
      "name":"Izor"
    },
    {
      "name":"Ihvan"
    },
    {
      "name":"Van Sthumpfen"
    },
    {
      "name":"Quyen"
    },
    {
      "name":"Deputy"
    },
    {
      "name":"Waierk"
    },
    {
      "name":"Odurg"
    },
    {
      "name":"Tog"
    },

    {
      "name":"Jingle"
    },
    {
      "name":"Cief"
    },
    {
      "name":"Cbik"
    },
    {
      "name":"Fumith"
    },
    {
      "name":"Jeot"
    },
    {
      "name":"Xigafh"
    },
    {
      "name":"Sokol"
    },
    {
      "name":"Duke"
    },
    {
      "name":"Dallas"
    },
    {
      "name":"Chains"
    },

    {
      "name":"Clover"
    },
    {
      "name":"Bonnie"
    },
    {
      "name":"Hoxton"
    },
    {
      "name":"Jacket"
    },
    {
      "name":"Aldstone"
    },
    {
      "name":"Dragan"
    },
    {
      "name":"Jiro"
    },
    {
      "name":"Dorian"
    },
    {
      "name":"Tiberius"
    },
    {
      "name":"Remus"
    }
  ],
  "countNouns":100,
  "nouns":[
    {
      "noun":"time"
    },
    {
      "noun":"day"
    },
    {
      "noun":"school"
    },
    {
      "noun":"student"
    },
    {
      "noun":"hand"
    },
    {
      "noun":"case"
    },
    {
      "noun":"question"
    },
    {
      "noun":"night"
    },
    {
      "noun":"point"
    },
    {
      "noun":"home"
    },

    {
      "noun":"water"
    },
    {
      "noun":"room"
    },
    {
      "noun":"study"
    },
    {
      "noun":"book"
    },
    {
      "noun":"eye"
    },
    {
      "noun":"job"
    },
    {
      "noun":"house"
    },
    {
      "noun":"head"
    },
    {
      "noun":"friend"
    },
    {
      "noun":"law"
    },

    {
      "noun":"body"
    },
    {
      "noun":"transformation"
    },
    {
      "noun":"face"
    },
    {
      "noun":"door"
    },
    {
      "noun":"morning"
    },
    {
      "noun":"air"
    },
    {
      "noun":"teacher"
    },
    {
      "noun":"force"
    },
    {
      "noun":"music"
    },
    {
      "noun":"market"
    },

    {
      "noun":"death"
    },
    {
      "noun":"experience"
    },
    {
      "noun":"sontrol"
    },
    {
      "noun":"field"
    },
    {
      "noun":"heart"
    },
    {
      "noun":"leader"
    },
    {
      "noun":"mind"
    },
    {
      "noun":"light"
    },
    {
      "noun":"road"
    },
    {
      "noun":"arm"
    },

    {
      "noun":"director"
    },
    {
      "noun":"paper"
    },
    {
      "noun":"ground"
    },
    {
      "noun":"official"
    },
    {
      "noun":"morning"
    },
    {
      "noun":"center"
    },
    {
      "noun":"table"
    },
    {
      "noun":"court"
    },
    {
      "noun":"street"
    },
    {
      "noun":"picture"
    },

    {
      "noun":"doctor"
    },
    {
      "noun":"wall"
    },
    {
      "noun":"north"
    },
    {
      "noun":"worker"
    },
    {
      "noun":"tree"
    },
    {
      "noun":"window"
    },
    {
      "noun":"summer"
    },
    {
      "noun":"south"
    },
    {
      "noun":"campaign"
    },
    {
      "noun":"fire"
    },

    {
      "noun":"west"
    },
    {
      "noun":"bank"
    },
    {
      "noun":"goal"
    },
    {
      "noun":"order"
    },
    {
      "noun":"blood"
    },
    {
      "noun":"animal"
    },
    {
      "noun":"east"
    },
    {
      "noun":"artist"
    },
    {
      "noun":"disease"
    },
    {
      "noun":"trade"
    },

    {
      "noun":"skill"
    },
    {
      "noun":"crime"
    },
    {
      "noun":"authority"
    },
    {
      "noun":"gun"
    },
    {
      "noun":"rock"
    },
    {
      "noun":"memory"
    },
    {
      "noun":"seat"
    },
    {
      "noun":"impact"
    },
    {
      "noun":"charge"
    },
    {
      "noun":"fish"
    },

    {
      "noun":"evening"
    },
    {
      "noun":"throne"
    },
    {
      "noun":"trip"
    },
    {
      "noun":"past"
    },
    {
      "noun":"edge"
    },
    {
      "noun":"writer"
    },
    {
      "noun":"fear"
    },
    {
      "noun":"sea"
    },
    {
      "noun":"dream"
    },
    {
      "noun":"bar"
    },

    {
      "noun":"soldier"
    },
    {
      "noun":"heat"
    },
    {
      "noun":"fall"
    },
    {
      "noun":"skin"
    },
    {
      "noun":"machine"
    },
    {
      "noun":"kitchen"
    },
    {
      "noun":"painting"
    },
    {
      "noun":"scientist"
    },
    {
      "noun":"victim"
    },
    {
      "noun":"citizen"
    }
  ]
}
